tx_widgets/__init__.py
tx_widgets/files_scr.py
tx_widgets/input.py
tx_widgets/optionlist.py
tx_widgets/select_base.py
tx_widgets/select_widgets.py
tx_widgets/test_select.py
tx_widgets-0.2442.2.dist-info/METADATA
tx_widgets-0.2442.2.dist-info/WHEEL
tx_widgets-0.2442.2.dist-info/top_level.txt
tx_widgets-0.2442.2.dist-info/RECORD
