Metadata-Version: 2.1
Name: tx_widgets
Version: 0.2442.2
Summary: Textual Widgets collections.
Author-email: Louis RIVIERE <louis@riviere.xyz>
Project-URL: pypi, https://pypi.org/project/tx-widgets
Project-URL: repository, https://helixteamhub.cloud/dull-pot-216/projects/projects/repositories/tx_widgets/tree/alpha
Keywords: util
Classifier: Development Status :: 3 - Alpha
Classifier: Programming Language :: Python :: 3
Classifier: Operating System :: POSIX :: Linux
Classifier: Environment :: Console
Classifier: Intended Audience :: Developers
Classifier: License :: OSI Approved :: MIT License
Requires-Python: >=3.8
Requires-Dist: textual
Requires-Dist: pybrary
